{"professionOrOccupation": [{"id": "https://d-nb.info/gnd/4029050-5", "label": "Jurist"}, {"id": "https://d-nb.info/gnd/4033423-5", "label": "K\u00fcnstler"}, {"id": "https://d-nb.info/gnd/4188376-7", "label": "Violoncellist"}], "placeOfBirth": [{"id": "https://d-nb.info/gnd/4037372-1", "label": "Mannheim"}], "gender": [{"id": "https://d-nb.info/standards/vocab/gnd/gender#male", "label": "M\u00e4nnlich"}], "dateOfDeath": ["1846-09-07"], "dateOfBirth": ["1802-01-31"], "placeOfDeath": [{"id": "https://d-nb.info/gnd/4003191-3", "label": "Aschaffenburg"}], "type": ["DifferentiatedPerson", "AuthorityResource", "Person"], "@context": "http://lobid.org/gnd/context.jsonld", "gndSubjectCategory": [{"id": "https://d-nb.info/standards/vocab/gnd/gnd-sc#7.14p", "label": "Personen zu Recht"}, {"id": "https://d-nb.info/standards/vocab/gnd/gnd-sc#31.3p", "label": "Personen zu Architektur, Bautechnik"}], "oldAuthorityNumber": ["(DE-588c)4742941-0", "(DE-588a)116943343", "(DE-588a)100497373"], "geographicAreaCode": [{"id": "https://d-nb.info/standards/vocab/gnd/geographic-area-code#XA-DE", "label": "Deutschland"}], "biographicalOrHistoricalInformation": ["Dt. Architekturtheoretiker und Jurist"], "publication": ["Hoffstadt, Friedrich: Gothisches ABC-Buch, das ist Grundregeln des gothischen Styls f\u00fcr K*. - 1880", "Hoffstadt, Friedrich: Gothisches A. B. C. Buch. - 1840"], "describedBy": {"id": "https://d-nb.info/gnd/116943343/about", "license": {"id": "http://creativecommons.org/publicdomain/zero/1.0/", "label": "http://creativecommons.org/publicdomain/zero/1.0/"}, "dateModified": "2020-12-11T16:29:04.000", "descriptionLevel": {"id": "https://d-nb.info/standards/vocab/gnd/description-level#1", "label": "Allgemeines, Interdisziplin\u00e4re Allgemeinw\u00f6rter"}}, "gndIdentifier": "116943343", "id": "https://d-nb.info/gnd/116943343", "preferredName": "Hoffstadt, Friedrich", "wikipedia": [{"id": "https://de.wikipedia.org/wiki/Friedrich_Hoffstadt", "label": "https://de.wikipedia.org/wiki/Friedrich_Hoffstadt"}], "preferredNameEntityForThePerson": {"forename": ["Friedrich"], "surname": ["Hoffstadt"]}, "sameAs": [{"collection": {"abbr": "DE-M512", "name": "Bayerisches Musiker-Lexikon Online", "publisher": "Bayerisches Musiker-Lexikon Online", "icon": "https://bmlo.de/x/pic/favicon.gif", "id": "http://bmlo.de"}, "id": "http://bmlo.de/Q/GND=116943343"}, {"id": "http://isni.org/isni/0000000117767927", "collection": {"id": "http://isni.org"}}, {"id": "http://viaf.org/viaf/264144782960190386955", "collection": {"id": "http://www.wikidata.org/entity/Q54919", "abbr": "VIAF", "publisher": "OCLC", "icon": "http://viaf.org/viaf/images/viaf.ico", "name": "Virtual International Authority File (VIAF)"}}, {"collection": {"abbr": "ADB", "name": "Allgemeine Deutsche Biographie (ADB)", "publisher": "Historische Kommission bei der Bayerischen Akademie der Wissenschaften und Bayerische Staatsbibliothek", "icon": "https://www.deutsche-biographie.de/favicon.ico", "id": "http://www.deutsche-biographie.de"}, "id": "http://www.deutsche-biographie.de/pnd116943343.html#adbcontent"}, {"id": "http://www.wikidata.org/entity/Q1459769", "collection": {"id": "http://www.wikidata.org/entity/Q2013", "abbr": "WIKIDATA", "publisher": "Wikimedia Foundation Inc.", "icon": "https://www.wikidata.org/static/favicon/wikidata.ico", "name": "Wikidata"}}, {"collection": {"abbr": "DNB", "name": "Gemeinsame Normdatei (GND) im Katalog der Deutschen Nationalbibliothek", "publisher": "Deutsche Nationalbibliothek", "icon": "https://www.dnb.de/SiteGlobals/Frontend/DNBWeb/Images/favicon.png?__blob=normal&v=4", "id": "http://www.wikidata.org/entity/Q36578"}, "id": "https://d-nb.info/gnd/116943343/about"}, {"collection": {"abbr": "dewiki", "name": "Wikipedia (Deutsch)", "publisher": "Wikimedia Foundation Inc.", "icon": "https://de.wikipedia.org/static/favicon/wikipedia.ico", "id": "http://www.wikidata.org/entity/Q48183"}, "id": "https://de.wikipedia.org/wiki/Friedrich_Hoffstadt"}, {"collection": {"abbr": "DE-611", "name": "Kalliope Verbundkatalog", "publisher": "Staatsbibliothek zu Berlin - Preu\u00dfischer Kulturbesitz", "icon": "https://kalliope-verbund.info/img/favicon.ico", "id": "https://kalliope-verbund.info"}, "id": "https://kalliope-verbund.info/gnd/116943343"}, {"collection": {"abbr": "DDB", "name": "Deutsche Digitale Bibliothek", "publisher": "Deutsche Digitale Bibliothek", "icon": "https://www.deutsche-digitale-bibliothek.de/favicon.ico", "id": "http://www.wikidata.org/entity/Q621630"}, "id": "https://www.deutsche-digitale-bibliothek.de/person/gnd/116943343"}], "depiction": [{"id": "https://commons.wikimedia.org/wiki/Special:FilePath/FriedrichHoffstadtself1823.jpg", "url": "https://commons.wikimedia.org/wiki/File:FriedrichHoffstadtself1823.jpg?uselang=de", "thumbnail": "https://commons.wikimedia.org/wiki/Special:FilePath/FriedrichHoffstadtself1823.jpg?width=270"}]}