{"hasSpouse": [{"id": "https://d-nb.info/gnd/1242750622", "label": "Reyscher, Dorothea"}], "gender": [{"id": "https://d-nb.info/standards/vocab/gnd/gender#male", "label": "M\u00e4nnlich"}], "dateOfDeath": ["1880-04-01"], "placeOfDeath": [{"id": "https://d-nb.info/gnd/4069840-3", "label": "Cannstatt"}], "familialRelationship": [{"id": "https://d-nb.info/gnd/139113320", "label": "Reyscher, Karl"}, {"id": "https://d-nb.info/gnd/1242750622", "label": "Reyscher, Dorothea"}], "type": ["AuthorityResource", "DifferentiatedPerson", "Person"], "gndSubjectCategory": [{"id": "https://d-nb.info/standards/vocab/gnd/gnd-sc#16.5p", "label": "Personen der Geschichte (Politiker und historische Pers\u00f6nlichkeiten)"}], "oldAuthorityNumber": ["(DE-588a)131082760", "(DE-588a)11874478X", "(DE-588)131082760", "(DE-588c)4103747-9"], "geographicAreaCode": [{"id": "https://d-nb.info/standards/vocab/gnd/geographic-area-code#XA-DE", "label": "Deutschland"}], "biographicalOrHistoricalInformation": ["Dt. Jurist u. Staatsmann"], "publication": ["Reyscher, August L.: Die grundherrlichen Rechte des W\u00fcrttembergischen Adels", "Reyscher, August L.: Ueber die Bed\u00fcrfnisse unserer Zeit in der Gesetzgebung", "Reyscher, August L.: Erinnerungen aus alter und neuer Zeit (1802-1880)", "Der Schwabenspiegel oder schw\u00e4bisches Land- und Lehen-Rechbuch", "Reyscher, August L.: Beytr\u00e4ge zur Kunde des deutschen Rechts", "Sammlung altw\u00fcrtembergischer Statut\u00e4r-Rechte", "Reyscher, August L.: \u00dcber die Einf\u00fchrung der W\u00fcrttembergischen Gesetze in die neuen Lande*", "Reyscher, August L.: Drei verfassungberathende Landesversammlungen und mein Austritt aus *", "Reyscher, August L.: Das gesammte w\u00fcrttembergische Privatrecht. - 1836 - 1843", "Reyscher, August L.: Publicistische Versuche", "Der @Schwabenspiegel oder schw\u00e4bisches Land- und Lehen-Rechbuch"], "describedBy": {"id": "https://d-nb.info/gnd/11874478X/about", "license": {"id": "http://creativecommons.org/publicdomain/zero/1.0/", "label": "http://creativecommons.org/publicdomain/zero/1.0/"}, "dateModified": "2022-03-09T17:06:23.000", "descriptionLevel": {"id": "https://d-nb.info/standards/vocab/gnd/description-level#1", "label": "Allgemeines, Interdisziplin\u00e4re Allgemeinw\u00f6rter"}}, "gndIdentifier": "11874478X", "id": "https://d-nb.info/gnd/11874478X", "preferredName": "Reyscher, August Ludwig", "wikipedia": [{"id": "https://de.wikipedia.org/wiki/August_Ludwig_Reyscher", "label": "https://de.wikipedia.org/wiki/August_Ludwig_Reyscher"}], "preferredNameEntityForThePerson": {"forename": ["August Ludwig"], "surname": ["Reyscher"]}, "depiction": [{"id": "https://commons.wikimedia.org/wiki/Special:FilePath/August%20Ludwig%20Reyscher.jpg", "url": "https://commons.wikimedia.org/wiki/File:August%20Ludwig%20Reyscher.jpg?uselang=de", "thumbnail": "https://commons.wikimedia.org/wiki/Special:FilePath/August%20Ludwig%20Reyscher.jpg?width=270"}], "professionOrOccupation": [{"id": "https://d-nb.info/gnd/4046517-2", "label": "Politiker"}, {"id": "https://d-nb.info/gnd/4029050-5", "label": "Jurist"}], "placeOfBirth": [{"id": "https://d-nb.info/gnd/4210200-5", "label": "Unterriexingen"}], "dateOfBirth": ["1802-07-10"], "variantNameEntityForThePerson": [{"forename": ["Ludwig"], "surname": ["Reyscher"]}, {"forename": ["A. L."], "surname": ["Reyscher"]}, {"forename": ["D. A. L."], "surname": ["Reyscher"]}, {"forename": ["L."], "surname": ["Reyscher"]}, {"forename": ["August L."], "surname": ["Reischer"]}], "@context": "http://lobid.org/gnd/context.jsonld", "deprecatedUri": ["https://d-nb.info/gnd/131082760"], "variantName": ["Reyscher, L.", "Reischer, August L.", "Reyscher, D. A. L.", "Reyscher, Ludwig", "Reyscher, A. L."], "hasParent": [{"id": "https://d-nb.info/gnd/139113320", "label": "Reyscher, Karl"}], "sameAs": [{"id": "http://id.loc.gov/rwo/agents/n2020035730", "collection": {"id": "http://www.wikidata.org/entity/Q13219454", "abbr": "LC", "publisher": "Library of Congress", "icon": "http://www.loc.gov/favicon.ico", "name": "NACO Authority File"}}, {"id": "http://isni.org/isni/0000000082396168", "collection": {"id": "http://isni.org"}}, {"id": "http://viaf.org/viaf/57410082", "collection": {"id": "http://www.wikidata.org/entity/Q54919", "abbr": "VIAF", "publisher": "OCLC", "icon": "http://viaf.org/viaf/images/viaf.ico", "name": "Virtual International Authority File (VIAF)"}}, {"collection": {"abbr": "ADB", "name": "Allgemeine Deutsche Biographie (ADB)", "publisher": "Historische Kommission bei der Bayerischen Akademie der Wissenschaften und Bayerische Staatsbibliothek", "icon": "https://www.deutsche-biographie.de/favicon.ico", "id": "http://www.deutsche-biographie.de"}, "id": "http://www.deutsche-biographie.de/pnd11874478X.html#adbcontent"}, {"collection": {"abbr": "NDB", "name": "Neue Deutsche Biographie (NDB)", "publisher": "Historische Kommission bei der Bayerischen Akademie der Wissenschaften und Bayerische Staatsbibliothek", "icon": "https://www.deutsche-biographie.de/favicon.ico", "id": "http://www.deutsche-biographie.de"}, "id": "http://www.deutsche-biographie.de/pnd11874478X.html#ndbcontent"}, {"id": "http://www.wikidata.org/entity/Q100787", "collection": {"id": "http://www.wikidata.org/entity/Q2013", "abbr": "WIKIDATA", "publisher": "Wikimedia Foundation Inc.", "icon": "https://www.wikidata.org/static/favicon/wikidata.ico", "name": "Wikidata"}}, {"collection": {"abbr": "DNB", "name": "Gemeinsame Normdatei (GND) im Katalog der Deutschen Nationalbibliothek", "publisher": "Deutsche Nationalbibliothek", "icon": "https://www.dnb.de/SiteGlobals/Frontend/DNBWeb/Images/favicon.png?__blob=normal&v=4", "id": "http://www.wikidata.org/entity/Q36578"}, "id": "https://d-nb.info/gnd/11874478X/about"}, {"id": "https://d-nb.info/gnd/131082760", "collection": {"id": "http://www.wikidata.org/entity/Q36578", "abbr": "DNB", "publisher": "Deutsche Nationalbibliothek", "icon": "http://www.dnb.de/SiteGlobals/StyleBundles/Bilder/favicon.png?__blob=normal&v=1", "name": "Gemeinsame Normdatei (GND) im Katalog der Deutschen Nationalbibliothek"}}, {"collection": {"abbr": "dewiki", "name": "Wikipedia (Deutsch)", "publisher": "Wikimedia Foundation Inc.", "icon": "https://de.wikipedia.org/static/favicon/wikipedia.ico", "id": "http://www.wikidata.org/entity/Q48183"}, "id": "https://de.wikipedia.org/wiki/August_Ludwig_Reyscher"}, {"collection": {"abbr": "WIKISOURCE", "name": "Wikisource", "publisher": "Wikimedia Foundation Inc.", "icon": "https://wikisource.org/static/favicon/wikisource.ico", "id": "http://www.wikidata.org/entity/Q263"}, "id": "https://de.wikisource.org/wiki/August_Ludwig_Reyscher"}, {"collection": {"abbr": "DE-611", "name": "Kalliope Verbundkatalog", "publisher": "Staatsbibliothek zu Berlin - Preu\u00dfischer Kulturbesitz", "icon": "https://kalliope-verbund.info/img/favicon.ico", "id": "https://kalliope-verbund.info"}, "id": "https://kalliope-verbund.info/gnd/11874478X"}, {"collection": {"abbr": "ARCHIV-D", "name": "Archivportal-D", "publisher": "Deutsche Digitale Bibliothek", "icon": "https://www.archivportal-d.de/favicon.ico", "id": "https://www.archivportal-d.de"}, "id": "https://www.archivportal-d.de/person/gnd/11874478X"}, {"collection": {"abbr": "DDB", "name": "Deutsche Digitale Bibliothek", "publisher": "Deutsche Digitale Bibliothek", "icon": "https://www.deutsche-digitale-bibliothek.de/favicon.ico", "id": "http://www.wikidata.org/entity/Q621630"}, "id": "https://www.deutsche-digitale-bibliothek.de/person/gnd/11874478X"}]}